<?xml version="1.0" encoding="UTF-8"?>
<objects serializationModel="Studio.02.02.00">
	<object class="AudioFile" id="{304ae603-cb93-4f84-ae86-be3af585d76c}">
		<property name="assetPath">
			<value>amb_forest_day_background_loop.wav</value>
		</property>
		<property name="isStreaming">
			<value>true</value>
		</property>
		<property name="frequencyInKHz">
			<value>44.0999985</value>
		</property>
		<property name="channelCount">
			<value>2</value>
		</property>
		<property name="length">
			<value>52.879342403628115</value>
		</property>
		<relationship name="masterAssetFolder">
			<destination>{ef14b30b-1c7a-4c74-a81f-159458061e4a}</destination>
		</relationship>
	</object>
</objects>
